gh_map_pipelines/__init__.py
gh_map_pipelines/api_server.py
gh_map_pipelines/cli.py
gh_map_pipelines/cli_v2.py
gh_map_pipelines/dashboard.py
gh_map_pipelines/database_admin.py
gh_map_pipelines/github_api.py
gh_map_pipelines/github_api_v3.py
gh_map_pipelines/veracode.py
gh_map_pipelines-0.2.3.dist-info/METADATA
gh_map_pipelines-0.2.3.dist-info/WHEEL
gh_map_pipelines-0.2.3.dist-info/entry_points.txt
gh_map_pipelines-0.2.3.dist-info/RECORD
